<shapes name="mxgraph.aws2.storage_and_content_delivery">
<shape aspect="variable" h="56.88" name="AWS Import Export" strokewidth="inherit" w="57.76">
<connections>
	<constraint x="0.5" y="0" perimeter="0" name="N"/>
	<constraint x="0.5" y="1" perimeter="0" name="S"/>
	<constraint x="0.045" y="0.595" perimeter="0" name="W"/>
	<constraint x="1" y="0.595" perimeter="0" name="E"/>
	<constraint x="0" y="0.1" perimeter="0" name="NW"/>
	<constraint x="0.97" y="0.1" perimeter="0" name="NE"/>
	<constraint x="0.165" y="0.945" perimeter="0" name="SW"/>
	<constraint x="0.8" y="0.945" perimeter="0" name="SE"/>
</connections>
    <foreground>
        <save/>
        <save/>
        <save/>
        <fillcolor color="#8C3323"/>
        <path>
<move x="55.9" y="5.79"/>
<line x="55.9" y="8.41"/>
<curve x1="55.9" x2="43.4" x3="27.95" y1="11.61" y2="14.2" y3="14.2"/>
<curve x1="12.52" x2="0" x3="0" y1="14.2" y2="11.61" y3="8.41"/>
<line x="0" y="5.79"/>
<curve x1="0" x2="12.52" x3="27.95" y1="9" y2="11.59" y3="11.59"/>
<curve x1="43.4" x2="55.9" x3="55.9" y1="11.59" y2="9" y3="5.79"/>
<close/>
</path>
        <fillstroke/>
        <restore/>
        <rect/>
        <stroke/>
        <fillcolor color="#8C3323"/>
        <path>
<move x="55.9" y="5.79"/>
<line x="55.9" y="8.41"/>
<curve x1="55.9" x2="55.9" x3="55.88" y1="8.48" y2="8.55" y3="8.62"/>
<line x="55.88" y="6.01"/>
<curve x1="55.9" x2="55.9" x3="55.9" y1="5.94" y2="5.86" y3="5.79"/>
</path>
        <fillstroke/>
        <path>
<move x="55.89" y="6.01"/>
<line x="55.89" y="8.62"/>
<curve x1="55.87" x2="55.85" x3="55.82" y1="8.71" y2="8.79" y3="8.87"/>
<line x="55.82" y="6.26"/>
<curve x1="55.85" x2="55.87" x3="55.89" y1="6.17" y2="6.09" y3="6.01"/>
</path>
        <fillstroke/>
        <path>
<move x="55.82" y="6.26"/>
<line x="55.82" y="8.87"/>
<curve x1="55.77" x2="55.71" x3="55.63" y1="8.99" y2="9.11" y3="9.23"/>
<line x="55.63" y="6.6099997"/>
<curve x1="55.71" x2="55.77" x3="55.82" y1="6.5" y2="6.38" y3="6.26"/>
</path>
        <fillstroke/>
        <path>
<move x="55.63" y="6.61"/>
<line x="55.63" y="9.23"/>
<curve x1="53.710003" x2="42.06" x3="27.95" y1="12.039999" y2="14.199999" y3="14.199999"/>
<curve x1="12.530001" x2="0" x3="0" y1="14.199999" y2="11.609999" y3="8.409999"/>
<line x="0" y="5.789999"/>
<curve x1="0" x2="12.53" x3="27.95" y1="8.999999" y2="11.589999" y3="11.589999"/>
<curve x1="42.06" x2="53.71" x3="55.63" y1="11.59" y2="9.43" y3="6.61"/>
</path>
        <fillstroke/>
        <fillcolor color="#E15343"/>
        <path>
<move x="27.95" y="0"/>
<curve x1="43.4" x2="55.9" x3="55.9" y1="0" y2="2.59" y3="5.79"/>
<curve x1="55.9" x2="43.4" x3="27.95" y1="8.99" y2="11.59" y3="11.59"/>
<curve x1="12.530001" x2="0" x3="0" y1="11.59" y2="9" y3="5.79"/>
<curve x1="0" x2="12.53" x3="27.95" y1="2.58" y2="0" y3="0"/>
<close/>
</path>
        <fillstroke/>
        <fillcolor color="#8C3323"/>
        <path>
<move x="38.58" y="23.76"/>
<line x="38.58" y="26.37"/>
<line x="23.5" y="26.37"/>
<line x="23.32" y="23.6"/>
<close/>
</path>
        <fillstroke/>
        <path>
<move x="24.43" y="23.75"/>
<line x="23.5" y="26.37"/>
<line x="13.25" y="19.43"/>
<line x="12.8" y="16.37"/>
<close/>
</path>
        <fillstroke/>
        <path>
<move x="4.47" y="23.93"/>
<line x="3.87" y="26.79"/>
<line x="0.16" y="12.87"/>
<line x="0.16" y="10.25"/>
<close/>
</path>
        <fillstroke/>
        <rect h="2.62" w="9.38" x="3.87" y="24.17"/>
        <fillstroke/>
        <path>
<move x="55.74" y="10.25"/>
<line x="55.74" y="12.87"/>
<line x="51.75" y="27.92"/>
<line x="51.4" y="24.93"/>
<close/>
</path>
        <fillstroke/>
        <fillcolor color="#E15343"/>
        <path>
<move x="55.74" y="10.25"/>
<line x="51.75" y="25.310001"/>
<line x="38.58" y="16.400002"/>
<line x="38.58" y="23.760002"/>
<line x="23.5" y="23.76"/>
<line x="13.25" y="16.82"/>
<line x="13.25" y="24.17"/>
<line x="3.87" y="24.17"/>
<line x="0.15999985" y="10.25"/>
<curve x1="1.6799998" x2="13.54" x3="27.95" y1="13.16" y2="15.41" y3="15.41"/>
<curve x1="42.36" x2="54.23" x3="55.74" y1="15.41" y2="13.17" y3="10.25"/>
<close/>
</path>
        <fillstroke/>
        <fillcolor color="#8C3323"/>
        <path>
<move x="51.75" y="25.31"/>
<line x="51.75" y="27.92"/>
<line x="38.58" y="19.01"/>
<line x="38.58" y="16.4"/>
<close/>
</path>
        <fillstroke/>
        <path>
<move x="37.03" y="34.05"/>
<line x="37.03" y="36.67"/>
<line x="29.55" y="31.17"/>
<line x="29.55" y="28.55"/>
<close/>
</path>
        <fillstroke/>
        <path>
<move x="42.72" y="38.58"/>
<line x="42.72" y="41.19"/>
<line x="30.31" y="41.14"/>
<line x="30.31" y="38.53"/>
<close/>
</path>
        <fillstroke/>
        <path>
<move x="30.24" y="34.12"/>
<line x="30.24" y="36.73"/>
<line x="23.75" y="41.34"/>
<line x="23.75" y="38.73"/>
<close/>
</path>
        <fillstroke/>
        <rect h="2.62" w="13.07" x="2.58" y="39"/>
        <fillstroke/>
        <path>
<move x="57.76" y="33.66"/>
<line x="57.76" y="36.28"/>
<line x="42.72" y="46.34"/>
<line x="42.72" y="43.73"/>
<close/>
</path>
        <fillstroke/>
        <fillcolor color="#E15343"/>
        <path>
<move x="42.72" y="23.47"/>
<line x="57.76" y="33.66"/>
<line x="42.72" y="43.73"/>
<line x="42.72" y="38.58"/>
<line x="30.31" y="38.53"/>
<line x="37.03" y="34.05"/>
<line x="29.55" y="28.55"/>
<line x="42.72" y="28.61"/>
<close/>
</path>
        <fillstroke/>
        <path>
<move x="15.65" y="23.89"/>
<line x="22.23" y="28.34"/>
<line x="30.24" y="34.12"/>
<line x="23.87" y="38.65"/>
<line x="15.65" y="44.15"/>
<line x="15.65" y="39"/>
<line x="2.58" y="39"/>
<line x="2.58" y="29.03"/>
<line x="15.65" y="29.03"/>
<close/>
</path>
        <fillstroke/>
        <fillcolor color="#8C3323"/>
        <path>
<move x="23.87" y="38.65"/>
<line x="23.87" y="41.26"/>
<line x="15.65" y="46.76"/>
<line x="15.65" y="44.15"/>
<close/>
</path>
        <fillstroke/>
        <path>
<move x="47.44" y="46.35"/>
<line x="47.44" y="48.96"/>
<line x="46.52" y="52.79"/>
<line x="46.36" y="50.52"/>
<close/>
</path>
        <fillstroke/>
        <path>
<move x="9.93" y="50.62"/>
<line x="9.32" y="53.01"/>
<line x="7.58" y="46.46"/>
<line x="7.58" y="43.85"/>
<close/>
</path>
        <fillstroke/>
        <restore/>
        <rect/>
        <stroke/>
        <fillcolor color="#8C3323"/>
        <path>
<move x="46.52" y="50.18"/>
<line x="46.52" y="52.79"/>
<curve x1="46.52" x2="38.25" x3="27.95" y1="54.920002" y2="56.88" y3="56.88"/>
<curve x1="17.650002" x2="9.320002" x3="9.320002" y1="56.88" y2="55.16" y3="53.010002"/>
<line x="9.320002" y="50.4"/>
<curve x1="9.320002" x2="17.650002" x3="27.95" y1="52.54" y2="54.27" y3="54.27"/>
<curve x1="38.25" x2="46.52" x3="46.52" y1="54.27" y2="52.31" y3="50.18"/>
<close/>
</path>
        <fillstroke/>
        <restore/>
        <rect/>
        <stroke/>
        <fillcolor color="#8C3323"/>
        <path>
<move x="46.52" y="50.18"/>
<line x="46.52" y="52.79"/>
<curve x1="46.52" x2="46.52" x3="46.510002" y1="52.83" y2="52.870003" y3="52.91"/>
<line x="46.510002" y="50.29"/>
<curve x1="46.52" x2="46.52" x3="46.52" y1="50.25" y2="50.22" y3="50.18"/>
</path>
        <fillstroke/>
        <path>
<move x="46.51" y="50.29"/>
<line x="46.51" y="52.91"/>
<curve x1="46.5" x2="46.489998" x3="46.469997" y1="52.95" y2="53" y3="53.04"/>
<line x="46.469997" y="50.43"/>
<curve x1="46.49" x2="46.5" x3="46.51" y1="50.38" y2="50.34" y3="50.29"/>
</path>
        <fillstroke/>
        <path>
<move x="46.47" y="50.43"/>
<line x="46.47" y="53.04"/>
<curve x1="46.440002" x2="46.41" x3="46.36" y1="53.11" y2="53.170002" y3="53.24"/>
<line x="46.36" y="50.620003"/>
<curve x1="46.4" x2="46.44" x3="46.47" y1="50.56" y2="50.49" y3="50.43"/>
</path>
        <fillstroke/>
        <path>
<move x="46.36" y="50.62"/>
<line x="46.36" y="53.239998"/>
<curve x1="44.96" x2="37.53" x3="27.95" y1="55.219997" y2="56.879997" y3="56.879997"/>
<curve x1="17.650002" x2="9.320002" x3="9.320002" y1="56.879997" y2="55.159996" y3="53.019997"/>
<line x="9.180001" y="49.369995"/>
<curve x1="9.180001" x2="17.650002" x3="27.95" y1="51.509995" y2="54.269997" y3="54.269997"/>
<curve x1="37.53" x2="44.96" x3="46.36" y1="54.27" y2="52.61" y3="50.62"/>
</path>
        <fillstroke/>
        <fillcolor color="#E15343"/>
        <path>
<move x="41.46" y="42.96"/>
<line x="41.46" y="50.29"/>
<line x="47.44" y="46.350002"/>
<line x="46.52" y="50.18"/>
<curve x1="46.52" x2="38.25" x3="27.95" y1="52.31" y2="54.27" y3="54.27"/>
<curve x1="17.650002" x2="9.320002" x3="9.320002" y1="54.27" y2="52.54" y3="50.4"/>
<line x="7.580002" y="43.850002"/>
<line x="13.250002" y="43.850002"/>
<line x="13.250002" y="51.2"/>
<line x="24.830002" y="43.43"/>
<line x="41.46" y="42.96"/>
<close/>
</path>
        <fillstroke/>
    </foreground>
</shape>
<shape aspect="variable" h="72.0" name="AWS Storage Gateway" strokewidth="inherit" w="59.63">
<connections>
	<constraint x="0.5" y="0" perimeter="0" name="N"/>
	<constraint x="0.5" y="1" perimeter="0" name="S"/>
	<constraint x="0" y="0.5" perimeter="0" name="W"/>
	<constraint x="1" y="0.5" perimeter="0" name="E"/>
	<constraint x="0" y="0.21" perimeter="0" name="NW"/>
	<constraint x="1" y="0.21" perimeter="0" name="NE"/>
	<constraint x="0" y="0.79" perimeter="0" name="SW"/>
	<constraint x="1" y="0.79" perimeter="0" name="SE"/>
</connections>
    <foreground>
        <fillcolor color="#8C3123"/>
        <path>
<move x="29.81" y="52.85"/>
<line x="55.82" y="58.94"/>
<line x="55.82" y="22.2"/>
<line x="29.81" y="25.87"/>
<close/>
</path>
        <fillstroke/>
        <fillcolor color="#5E1F18"/>
        <path>
<move x="31.36" y="23.84"/>
<line x="37.14" y="24.83"/>
<line x="55.82" y="22.2"/>
<line x="37.31" y="16.65"/>
<line x="31.53" y="18.06"/>
<close/>
</path>
        <fillstroke/>
        <fillcolor color="#E05243"/>
        <path>
<move x="59.63" y="14.91"/>
<line x="59.62" y="14.9"/>
<line x="55.82" y="13.01"/>
<line x="29.81" y="0.0"/>
<line x="29.81" y="14.4"/>
<line x="29.81" y="72.0"/>
<line x="38.73" y="67.54"/>
<line x="38.73" y="17.08"/>
<line x="55.82" y="22.2"/>
<line x="55.82" y="58.99"/>
<line x="59.62" y="57.1"/>
<line x="59.62" y="23.34"/>
<line x="59.63" y="23.35"/>
<close/>
</path>
        <fillstroke/>
        <fillcolor color="#8C3123"/>
        <path>
<move x="13.93" y="64.06"/>
<line x="29.81" y="72.0"/>
<line x="29.81" y="0.0"/>
<line x="13.93" y="7.94"/>
<close/>
</path>
        <fillstroke/>
        <path>
<move x="8.36" y="61.28"/>
<line x="0.0" y="57.1"/>
<line x="0.0" y="14.9"/>
<line x="8.36" y="10.72"/>
<close/>
</path>
        <fillstroke/>
        <fillcolor color="#E05243"/>
        <path>
<move x="13.93" y="59.62"/>
<line x="8.36" y="61.11"/>
<line x="8.36" y="10.72"/>
<line x="13.93" y="12.23"/>
<close/>
</path>
        <fillstroke/>
    </foreground>
</shape>
<shape aspect="variable" h="72.0" name="CloudFront" strokewidth="inherit" w="59.86">
<connections>
	<constraint x="0.5" y="0" perimeter="0" name="N"/>
	<constraint x="0.5" y="1" perimeter="0" name="S"/>
	<constraint x="0" y="0.5" perimeter="0" name="W"/>
	<constraint x="1" y="0.5" perimeter="0" name="E"/>
	<constraint x="0" y="0.21" perimeter="0" name="NW"/>
	<constraint x="1" y="0.21" perimeter="0" name="NE"/>
	<constraint x="0" y="0.79" perimeter="0" name="SW"/>
	<constraint x="1" y="0.79" perimeter="0" name="SE"/>
</connections>
    <foreground>
        <fillcolor color="#8C3123"/>
        <path>
<move x="38.8" y="29.85"/>
<line x="52.65" y="28.79"/>
<line x="52.65" y="11.36"/>
<line x="38.8" y="14.96"/>
<close/>
</path>
        <fillstroke/>
        <fillcolor color="#E05243"/>
        <path>
<move x="44.21" y="27.62"/>
<line x="29.79" y="25.53"/>
<line x="29.79" y="0.0"/>
<line x="44.21" y="7.22"/>
<close/>
</path>
        <fillstroke/>
        <path>
<move x="59.86" y="29.87"/>
<line x="52.65" y="28.82"/>
<line x="52.65" y="11.36"/>
<line x="59.86" y="14.96"/>
<close/>
</path>
        <fillstroke/>
        <fillcolor color="#5E1F18"/>
        <path>
<move x="38.8" y="29.85"/>
<line x="52.49" y="28.8"/>
<line x="59.86" y="29.87"/>
<line x="46.63" y="30.66"/>
<close/>
</path>
        <fillstroke/>
        <fillcolor color="#8C3123"/>
        <path>
<move x="38.8" y="42.15"/>
<line x="52.65" y="43.21"/>
<line x="52.65" y="60.64"/>
<line x="38.8" y="57.04"/>
<close/>
</path>
        <fillstroke/>
        <fillcolor color="#E05243"/>
        <path>
<move x="44.21" y="44.38"/>
<line x="29.79" y="46.47"/>
<line x="29.79" y="72.0"/>
<line x="44.21" y="64.78"/>
<close/>
</path>
        <fillstroke/>
        <path>
<move x="59.71" y="42.13"/>
<line x="52.51" y="43.18"/>
<line x="52.51" y="60.64"/>
<line x="59.71" y="57.04"/>
<close/>
</path>
        <fillstroke/>
        <fillcolor color="#F2B0A9"/>
        <path>
<move x="38.8" y="42.15"/>
<line x="52.49" y="43.2"/>
<line x="59.86" y="42.13"/>
<line x="46.63" y="41.34"/>
<close/>
</path>
        <fillstroke/>
        <fillcolor color="#E05243"/>
        <path>
<move x="20.91" y="29.85"/>
<line x="7.07" y="28.79"/>
<line x="7.07" y="11.36"/>
<line x="20.91" y="14.96"/>
<close/>
</path>
        <fillstroke/>
        <fillcolor color="#8C3123"/>
        <path>
<move x="15.5" y="27.62"/>
<line x="29.93" y="25.53"/>
<line x="29.93" y="0.0"/>
<line x="15.5" y="7.22"/>
<close/>
</path>
        <fillstroke/>
        <path>
<move x="0.0" y="29.87"/>
<line x="7.21" y="28.82"/>
<line x="7.21" y="11.36"/>
<line x="0.0" y="14.96"/>
<close/>
</path>
        <fillstroke/>
        <fillcolor color="#5E1F18"/>
        <path>
<move x="21.05" y="29.85"/>
<line x="7.36" y="28.8"/>
<line x="0.0" y="29.87"/>
<line x="13.22" y="30.66"/>
<close/>
</path>
        <fillstroke/>
        <fillcolor color="#E05243"/>
        <path>
<move x="20.91" y="42.15"/>
<line x="7.07" y="43.21"/>
<line x="7.07" y="60.64"/>
<line x="20.91" y="57.04"/>
<close/>
</path>
        <fillstroke/>
        <fillcolor color="#8C3123"/>
        <path>
<move x="15.5" y="44.38"/>
<line x="29.93" y="46.47"/>
<line x="29.93" y="72.0"/>
<line x="15.5" y="64.78"/>
<close/>
</path>
        <fillstroke/>
        <path>
<move x="0.0" y="42.13"/>
<line x="7.21" y="43.18"/>
<line x="7.21" y="60.64"/>
<line x="0.0" y="57.04"/>
<close/>
</path>
        <fillstroke/>
        <fillcolor color="#F2B0A9"/>
        <path>
<move x="21.05" y="42.15"/>
<line x="7.36" y="43.2"/>
<line x="0.0" y="42.13"/>
<line x="13.22" y="41.34"/>
<close/>
</path>
        <fillstroke/>
        <path>
<move x="44.36" y="44.38"/>
<line x="29.93" y="42.97"/>
<line x="15.5" y="44.38"/>
<line x="29.93" y="46.5"/>
<close/>
</path>
        <fillstroke/>
        <fillcolor color="#5E1F18"/>
        <path>
<move x="44.36" y="27.62"/>
<line x="29.93" y="29.01"/>
<line x="15.5" y="27.62"/>
<line x="29.93" y="25.53"/>
<close/>
</path>
        <fillstroke/>
    </foreground>
</shape>
<shape aspect="variable" h="57.23" name="CloudFront Download Distribution" strokewidth="inherit" w="55.2">
<connections>
	<constraint x="0.5" y="0" perimeter="0" name="N"/>
	<constraint x="0.5" y="1" perimeter="0" name="S"/>
	<constraint x="0" y="0.5" perimeter="0" name="W"/>
	<constraint x="1" y="0.5" perimeter="0" name="E"/>
	<constraint x="0.145" y="0.145" perimeter="0" name="NW"/>
	<constraint x="0.855" y="0.145" perimeter="0" name="NE"/>
	<constraint x="0.145" y="0.855" perimeter="0" name="SW"/>
	<constraint x="0.855" y="0.855" perimeter="0" name="SE"/>
</connections>
    <foreground>
        <save/>
        <save/>
        <fillcolor color="#E05243"/>
        <path>
<move x="27.6" y="0.0"/>
<curve x1="42.84" x2="55.2" x3="55.2" y1="0.0" y2="12.26" y3="27.37"/>
<curve x1="55.2" x2="42.84" x3="27.6" y1="42.5" y2="54.75" y3="54.75"/>
<curve x1="12.360001" x2="0.0" x3="0.0" y1="54.75" y2="42.5" y3="27.37"/>
<curve x1="0.0" x2="12.36" x3="27.6" y1="12.26" y2="0.0" y3="0.0"/>
<close/>
</path>
        <fillstroke/>
        <restore/>
        <rect/>
        <stroke/>
        <fillcolor color="#8C3123"/>
        <path>
<move x="55.2" y="27.37"/>
<line x="55.2" y="29.85"/>
<curve x1="55.2" x2="42.84" x3="27.6" y1="44.96" y2="57.22" y3="57.22"/>
<curve x1="12.35" x2="0.0" x3="0.0" y1="57.22" y2="44.96" y3="29.85"/>
<line x="-0.01" y="27.37"/>
<curve x1="-0.01" x2="12.349999" x3="27.59" y1="42.49" y2="54.75" y3="54.75"/>
<curve x1="42.84" x2="55.2" x3="55.2" y1="54.75" y2="42.49" y3="27.37"/>
<close/>
</path>
        <fillstroke/>
        <restore/>
        <rect/>
        <stroke/>
        <fillcolor color="#8C3123"/>
        <path>
<move x="55.2" y="27.37"/>
<line x="55.2" y="29.85"/>
<curve x1="55.2" x2="55.100002" x3="54.89" y1="31.24" y2="32.6" y3="33.93"/>
<line x="54.89" y="31.460001"/>
<curve x1="55.1" x2="55.2" x3="55.2" y1="30.13" y2="28.77" y3="27.37"/>
</path>
        <fillstroke/>
        <path>
<move x="54.89" y="31.46"/>
<line x="54.89" y="33.93"/>
<curve x1="54.66" x2="54.29" x3="53.8" y1="35.49" y2="37.010002" y3="38.47"/>
<line x="53.8" y="35.99"/>
<curve x1="54.29" x2="54.66" x3="54.89" y1="34.54" y2="33.02" y3="31.46"/>
</path>
        <fillstroke/>
        <path>
<move x="53.8" y="35.99"/>
<line x="53.8" y="38.47"/>
<curve x1="53.23" x2="52.489998" x3="51.6" y1="40.190002" y2="41.83" y3="43.38"/>
<line x="51.6" y="40.91"/>
<curve x1="52.49" x2="53.23" x3="53.8" y1="39.36" y2="37.72" y3="35.99"/>
</path>
        <fillstroke/>
        <path>
<move x="51.6" y="40.91"/>
<line x="51.6" y="43.38"/>
<curve x1="46.85" x2="37.879997" x3="27.599998" y1="51.65" y2="57.230003" y3="57.230003"/>
<curve x1="12.359999" x2="-1.9073486E-6" x3="-1.9073486E-6" y1="57.230003" y2="44.97" y3="29.850004"/>
<line x="0.0" y="27.37"/>
<curve x1="0.0" x2="12.36" x3="27.6" y1="42.5" y2="54.75" y3="54.75"/>
<curve x1="37.88" x2="46.85" x3="51.6" y1="54.75" y2="49.18" y3="40.91"/>
</path>
        <fillstroke/>
        <fillcolor color="#FFFFFF"/>
        <path>
<move x="38.28" y="31.89"/>
<line x="40.649998" y="31.89"/>
<line x="40.649998" y="33.86"/>
<line x="38.28" y="33.86"/>
<line x="38.28" y="31.89"/>
<close/>
<move x="32.55" y="4.66"/>
<line x="35.52" y="4.66"/>
<line x="35.52" y="7.6"/>
<line x="33.54" y="7.6"/>
<line x="33.54" y="6.62"/>
<line x="32.55" y="6.62"/>
<line x="32.55" y="4.66"/>
<close/>
<move x="33.54" y="21.2"/>
<line x="33.54" y="17.32"/>
<line x="35.52" y="17.32"/>
<line x="35.510002" y="21.2"/>
<line x="33.54" y="21.2"/>
<close/>
<move x="35.51" y="24.12"/>
<line x="35.51" y="28.0"/>
<line x="33.539997" y="28.0"/>
<line x="33.54" y="24.11"/>
<line x="35.51" y="24.12"/>
<close/>
<move x="33.54" y="14.4"/>
<line x="33.54" y="10.509999"/>
<line x="35.52" y="10.509999"/>
<line x="35.52" y="14.4"/>
<line x="33.54" y="14.4"/>
<close/>
<move x="25.63" y="4.66"/>
<line x="29.59" y="4.66"/>
<line x="29.59" y="6.62"/>
<line x="25.630001" y="6.62"/>
<line x="25.63" y="4.66"/>
<close/>
<move x="19.7" y="4.66"/>
<line x="22.66" y="4.66"/>
<line x="22.66" y="6.62"/>
<line x="21.67" y="6.62"/>
<line x="21.67" y="7.6"/>
<line x="19.7" y="7.6"/>
<line x="19.7" y="4.66"/>
<close/>
<move x="19.7" y="10.52"/>
<line x="21.67" y="10.52"/>
<line x="21.67" y="14.42"/>
<line x="19.7" y="14.42"/>
<line x="19.7" y="10.52"/>
<close/>
<move x="19.7" y="17.35"/>
<line x="21.67" y="17.35"/>
<line x="21.67" y="21.25"/>
<line x="19.7" y="21.25"/>
<line x="19.7" y="17.35"/>
<close/>
<move x="19.7" y="24.17"/>
<line x="21.67" y="24.17"/>
<line x="21.67" y="28.07"/>
<line x="19.7" y="28.07"/>
<line x="19.7" y="24.17"/>
<close/>
<move x="14.56" y="31.97"/>
<line x="16.93" y="31.97"/>
<line x="16.93" y="33.94"/>
<line x="14.56" y="33.94"/>
<line x="14.56" y="31.97"/>
<close/>
<move x="12.78" y="33.76"/>
<line x="12.78" y="33.94"/>
<line x="12.61" y="33.94"/>
<line x="11.5199995" y="35.03"/>
<line x="8.389999" y="31.97"/>
<line x="12.779999" y="31.97"/>
<line x="12.779999" y="33.51"/>
<line x="12.909999" y="33.629997"/>
<line x="12.78" y="33.76"/>
<close/>
<move x="17.28" y="40.66"/>
<line x="13.990001" y="37.44"/>
<line x="15.370001" y="36.039997"/>
<line x="18.66" y="39.26"/>
<line x="17.28" y="40.66"/>
<close/>
<move x="18.71" y="31.97"/>
<line x="19.699999" y="31.97"/>
<line x="19.699999" y="30.99"/>
<line x="21.669998" y="30.99"/>
<line x="21.669998" y="33.94"/>
<line x="18.71" y="33.94"/>
<line x="18.71" y="31.97"/>
<close/>
<move x="23.03" y="46.28"/>
<line x="19.740002" y="43.07"/>
<line x="21.130001" y="41.67"/>
<line x="24.420002" y="44.879997"/>
<line x="23.03" y="46.28"/>
<close/>
<move x="27.6" y="50.74"/>
<line x="25.5" y="48.690002"/>
<line x="26.88" y="47.29"/>
<line x="27.599998" y="47.99"/>
<line x="28.309998" y="47.29"/>
<line x="29.699997" y="48.690002"/>
<line x="27.6" y="50.74"/>
<close/>
<move x="32.17" y="46.27"/>
<line x="30.779999" y="44.87"/>
<line x="34.07" y="41.64"/>
<line x="35.46" y="43.03"/>
<line x="32.17" y="46.27"/>
<close/>
<move x="36.5" y="33.86"/>
<line x="33.54" y="33.86"/>
<line x="33.54" y="30.91"/>
<line x="35.510002" y="30.91"/>
<line x="35.510002" y="31.89"/>
<line x="36.500004" y="31.89"/>
<line x="36.5" y="33.86"/>
<close/>
<move x="37.93" y="40.61"/>
<line x="36.54" y="39.21"/>
<line x="39.83" y="35.98"/>
<line x="41.22" y="37.38"/>
<line x="37.93" y="40.61"/>
<close/>
<move x="43.69" y="34.95"/>
<line x="42.6" y="33.86"/>
<line x="42.43" y="33.86"/>
<line x="42.43" y="33.68"/>
<line x="42.3" y="33.56"/>
<line x="42.43" y="33.43"/>
<line x="42.43" y="31.89"/>
<line x="46.81" y="31.89"/>
<line x="43.69" y="34.95"/>
<close/>
</path>
        <fillstroke/>
    </foreground>
</shape>
<shape aspect="variable" h="56.81" name="CloudFront Edge Location" strokewidth="inherit" w="52.2">
<connections>
	<constraint x="0.25" y="0" perimeter="0" name="N1"/>
	<constraint x="0.5" y="0" perimeter="0" name="N"/>
	<constraint x="0.75" y="0" perimeter="0" name="N2"/>
	<constraint x="0.25" y="1" perimeter="0" name="S1"/>
	<constraint x="0.5" y="1" perimeter="0" name="S"/>
	<constraint x="0.75" y="1" perimeter="0" name="S2"/>
	<constraint x="0" y="0.25" perimeter="0" name="W1"/>
	<constraint x="0" y="0.5" perimeter="0" name="W"/>
	<constraint x="0" y="0.75" perimeter="0" name="W2"/>
	<constraint x="1" y="0.25" perimeter="0" name="E1"/>
	<constraint x="1" y="0.5" perimeter="0" name="E"/>
	<constraint x="1" y="0.75" perimeter="0" name="E2"/>
	<constraint x="0" y="0" perimeter="0" name="NW"/>
	<constraint x="1" y="0" perimeter="0" name="NE"/>
	<constraint x="0" y="1" perimeter="0" name="SW"/>
	<constraint x="1" y="1" perimeter="0" name="SE"/>
</connections>
    <foreground>
        <save/>
        <save/>
        <save/>
        <save/>
        <fillcolor color="#8C3123"/>
        <rect h="3.18" w="15.48" x="18.0" y="16.82"/>
        <fillstroke/>
        <restore/>
        <rect/>
        <stroke/>
        <fillcolor color="#8C3123"/>
        <path>
<move x="52.2" y="26.66"/>
<line x="52.2" y="29.84"/>
<curve x1="47.61" x2="41.39" x3="33.47" y1="27.74" y2="25.78" y3="25.09"/>
<line x="33.47" y="21.91"/>
<curve x1="41.39" x2="47.61" x3="52.2" y1="22.6" y2="24.56" y3="26.66"/>
<close/>
</path>
        <fillstroke/>
        <restore/>
        <rect/>
        <stroke/>
        <fillcolor color="#8C3123"/>
        <path>
<move x="52.2" y="26.66"/>
<line x="52.2" y="29.84"/>
<curve x1="47.620003" x2="41.4" x3="33.480003" y1="27.74" y2="25.78" y3="25.09"/>
<line x="33.480003" y="21.91"/>
<curve x1="41.4" x2="47.62" x3="52.2" y1="22.6" y2="24.57" y3="26.66"/>
</path>
        <fillstroke/>
        <restore/>
        <rect/>
        <stroke/>
        <fillcolor color="#8C3123"/>
        <path>
<move x="18.0" y="22.42"/>
<line x="18.0" y="25.6"/>
<curve x1="10.52" x2="4.3900003" x3="0.0" y1="26.83" y2="29.310001" y3="31.62"/>
<line x="0.0" y="28.45"/>
<curve x1="4.38" x2="10.52" x3="18.0" y1="26.14" y2="23.65" y3="22.42"/>
<close/>
</path>
        <fillstroke/>
        <restore/>
        <rect/>
        <stroke/>
        <fillcolor color="#8C3123"/>
        <path>
<move x="18.0" y="22.42"/>
<line x="18.0" y="25.6"/>
<curve x1="10.530001" x2="4.3900003" x3="0.0" y1="26.83" y2="29.310001" y3="31.62"/>
<line x="0.0" y="28.45"/>
<curve x1="4.39" x2="10.53" x3="18.0" y1="26.14" y2="23.65" y3="22.42"/>
</path>
        <fillstroke/>
        <fillcolor color="#E05243"/>
        <path>
<move x="52.2" y="0.0"/>
<line x="52.2" y="28.46"/>
<line x="52.2" y="26.66"/>
<curve x1="47.620003" x2="41.4" x3="33.480003" y1="24.57" y2="22.6" y3="21.91"/>
<line x="33.480003" y="16.82"/>
<line x="18.0" y="16.82"/>
<line x="18.0" y="22.42"/>
<curve x1="10.530001" x2="4.3900003" x3="0.0" y1="23.65" y2="26.14" y3="28.45"/>
<line x="0.0" y="0.0"/>
<line x="52.2" y="0.0"/>
<close/>
</path>
        <fillstroke/>
        <path>
<move x="33.48" y="27.28"/>
<curve x1="41.329998" x2="47.58" x3="52.199997" y1="27.99" y2="29.970001" y3="32.09"/>
<line x="52.209995" y="53.63"/>
<line x="0.0" y="53.63"/>
<line x="0.0" y="33.62"/>
<curve x1="4.32" x2="10.41" x3="18.0" y1="31.349998" y2="28.91" y3="27.71"/>
<line x="18.0" y="34.0"/>
<line x="33.48" y="34.0"/>
<line x="33.48" y="27.28"/>
<close/>
</path>
        <fillstroke/>
        <fillcolor color="#8C3123"/>
        <rect h="3.18" w="52.2" x="0.0" y="53.63"/>
        <fillstroke/>
    </foreground>
</shape>
<shape aspect="variable" h="57.03" name="CloudFront Streaming Distribution" strokewidth="inherit" w="55.01">
<connections>
	<constraint x="0.5" y="0" perimeter="0" name="N"/>
	<constraint x="0.5" y="1" perimeter="0" name="S"/>
	<constraint x="0" y="0.5" perimeter="0" name="W"/>
	<constraint x="1" y="0.5" perimeter="0" name="E"/>
	<constraint x="0.145" y="0.145" perimeter="0" name="NW"/>
	<constraint x="0.855" y="0.145" perimeter="0" name="NE"/>
	<constraint x="0.145" y="0.855" perimeter="0" name="SW"/>
	<constraint x="0.855" y="0.855" perimeter="0" name="SE"/>
</connections>
    <foreground>
        <save/>
        <save/>
        <fillcolor color="#E05243"/>
        <path>
<move x="27.5" y="0.0"/>
<curve x1="42.69" x2="55.010002" x3="55.010002" y1="0.0" y2="12.22" y3="27.29"/>
<curve x1="55.010002" x2="42.7" x3="27.500002" y1="42.350002" y2="54.57" y3="54.57"/>
<curve x1="12.300003" x2="0.0" x3="0.0" y1="54.57" y2="42.35" y3="27.29"/>
<curve x1="0.0" x2="12.31" x3="27.5" y1="12.22" y2="0.0" y3="0.0"/>
<close/>
</path>
        <fillstroke/>
        <restore/>
        <rect/>
        <stroke/>
        <fillcolor color="#8C3123"/>
        <path>
<move x="55.0" y="27.29"/>
<line x="55.0" y="29.75"/>
<curve x1="55.0" x2="42.69" x3="27.5" y1="44.82" y2="57.04" y3="57.04"/>
<curve x1="12.310001" x2="0.0" x3="0.0" y1="57.04" y2="44.82" y3="29.75"/>
<line x="0.0" y="27.29"/>
<curve x1="0.0" x2="12.31" x3="27.5" y1="42.36" y2="54.57" y3="54.57"/>
<curve x1="42.69" x2="55.0" x3="55.0" y1="54.57" y2="42.36" y3="27.29"/>
<close/>
</path>
        <fillstroke/>
        <restore/>
        <rect/>
        <stroke/>
        <fillcolor color="#8C3123"/>
        <path>
<move x="55.01" y="27.29"/>
<line x="55.01" y="29.75"/>
<curve x1="55.01" x2="54.91" x3="54.71" y1="31.14" y2="32.5" y3="33.82"/>
<line x="54.71" y="31.36"/>
<curve x1="54.91" x2="55.01" x3="55.01" y1="30.03" y2="28.67" y3="27.29"/>
</path>
        <fillstroke/>
        <path>
<move x="54.71" y="31.36"/>
<line x="54.71" y="33.82"/>
<curve x1="54.469997" x2="54.11" x3="53.62" y1="35.37" y2="36.89" y3="38.34"/>
<line x="53.62" y="35.87"/>
<curve x1="54.11" x2="54.47" x3="54.71" y1="34.42" y2="32.91" y3="31.36"/>
</path>
        <fillstroke/>
        <path>
<move x="53.62" y="35.87"/>
<line x="53.62" y="38.34"/>
<curve x1="53.05" x2="52.309998" x3="51.42" y1="40.05" y2="41.69" y3="43.24"/>
<line x="51.42" y="40.77"/>
<curve x1="52.31" x2="53.05" x3="53.62" y1="39.23" y2="37.59" y3="35.87"/>
</path>
        <fillstroke/>
        <path>
<move x="51.42" y="40.77"/>
<line x="51.42" y="43.24"/>
<curve x1="46.69" x2="37.75" x3="27.5" y1="51.48" y2="57.03" y3="57.03"/>
<curve x1="12.31" x2="0.0" x3="0.0" y1="57.03" y2="44.82" y3="29.749998"/>
<line x="0.0" y="27.289997"/>
<curve x1="0.0" x2="12.31" x3="27.5" y1="42.35" y2="54.57" y3="54.57"/>
<curve x1="37.75" x2="46.69" x3="51.42" y1="54.57" y2="49.01" y3="40.77"/>
</path>
        <fillstroke/>
        <fillcolor color="#FFFFFF"/>
        <path>
<move x="34.65" y="5.05"/>
<line x="20.36" y="5.05"/>
<line x="20.36" y="32.28"/>
<line x="10.16" y="32.28"/>
<line x="27.5" y="49.22"/>
<line x="44.85" y="32.2"/>
<line x="34.65" y="32.2"/>
<line x="34.65" y="5.05"/>
<close/>
<move x="40.05" y="34.16"/>
<line x="27.5" y="46.48"/>
<line x="14.97" y="34.24"/>
<line x="22.33" y="34.24"/>
<line x="22.33" y="7.01"/>
<line x="32.69" y="7.01"/>
<line x="32.68" y="34.15"/>
<line x="40.05" y="34.15"/>
<close/>
</path>
        <fillstroke/>
    </foreground>
</shape>
<shape aspect="variable" h="66.0" name="EBS" strokewidth="inherit" w="46.79">
<connections>
	<constraint x="0.5" y="0" perimeter="0" name="N"/>
	<constraint x="0.5" y="1" perimeter="0" name="S"/>
	<constraint x="0" y="0.5" perimeter="0" name="W"/>
	<constraint x="1" y="0.5" perimeter="0" name="E"/>
	<constraint x="0.16" y="0" perimeter="0" name="NW"/>
	<constraint x="0.84" y="0" perimeter="0" name="NE"/>
	<constraint x="0" y="1" perimeter="0" name="SW"/>
	<constraint x="1" y="1" perimeter="0" name="SE"/>
</connections>
    <foreground>
        <fillcolor color="#E15343"/>
        <rect h="51.37" w="46.79" x="0.0" y="12.14"/>
        <fillstroke/>
        <path>
<move x="39.36" y="0.0"/>
<line x="7.47" y="0.0"/>
<line x="0.61" y="6.42"/>
<line x="1.1" y="6.42"/>
<line x="45.72" y="6.42"/>
<close/>
</path>
        <fillstroke/>
        <fillcolor color="#8C3323"/>
        <rect h="2.49" w="46.79" x="0.0" y="63.51"/>
        <fillstroke/>
        <rect h="2.49" w="45.12" x="0.61" y="6.42"/>
        <fillstroke/>
    </foreground>
</shape>
<shape aspect="variable" h="65.0" name="EBS Snapshot" strokewidth="inherit" w="53.33">
<connections>
	<constraint x="0.5" y="0" perimeter="0" name="N"/>
	<constraint x="0.5" y="1" perimeter="0" name="S"/>
	<constraint x="0.045" y="0.5" perimeter="0" name="W"/>
	<constraint x="0.955" y="0.5" perimeter="0" name="E"/>
	<constraint x="0.24" y="0.045" perimeter="0" name="NW"/>
	<constraint x="0.76" y="0.045" perimeter="0" name="NE"/>
	<constraint x="0.17" y="0.945" perimeter="0" name="SW"/>
	<constraint x="0.83" y="0.945" perimeter="0" name="SE"/>
</connections>
    <foreground>
        <save/>
        <save/>
        <save/>
        <save/>
        <fillcolor color="none"/>
        <path>
<move x="33.24" y="26.78"/>
<curve x1="37.27" x2="40.940002" x3="44.0" y1="26.52" y2="26.04" y3="25.380001"/>
<curve x1="40.66" x2="36.83" x3="33.24" y1="26.07" y2="26.53" y3="26.78"/>
<close/>
</path>
        <stroke/>
        <path>
<move x="44.51" y="22.38"/>
<curve x1="41.48" x2="37.76" x3="33.62" y1="23.05" y2="23.56" y3="23.83"/>
<curve x1="38.27" x2="41.82" x3="44.51" y1="23.54" y2="23.01" y3="22.38"/>
<close/>
</path>
        <stroke/>
        <path>
<move x="26.52" y="24.06"/>
<curve x1="19.99" x2="14.02" x3="9.450001" y1="24.06" y2="23.5" y3="22.57"/>
<curve x1="13.78" x2="19.58" x3="26.52" y1="23.5" y2="24.1" y3="24.06"/>
<close/>
</path>
        <stroke/>
        <path>
<move x="26.65" y="26.98"/>
<curve x1="11.099999" x2="1.3799992" x3="0.1099987" y1="26.789999" y2="23.96" y3="20.98"/>
<line x="0.1299987" y="21.039999"/>
<curve x1="1.58" x2="12.89" x3="26.65" y1="24.39" y2="26.98" y3="26.98"/>
<close/>
</path>
        <stroke/>
        <fillcolor color="#146EB4"/>
        <path>
<move x="0.09" y="20.93"/>
<curve x1="0.1" x2="0.11" x3="0.13" y1="20.970001" y2="21.01" y3="21.04"/>
<line x="0.11" y="20.980001"/>
<curve x1="0.1" x2="0.1" x3="0.09" y1="20.96" y2="20.95" y3="20.93"/>
<close/>
</path>
        <fillstroke/>
        <path>
<move x="0.06" y="20.84"/>
<curve x1="0.04" x2="0.02" x3="0.0" y1="20.78" y2="20.710001" y3="20.64"/>
<curve x1="0.02" x2="0.04" x3="0.06" y1="20.71" y2="20.78" y3="20.84"/>
<close/>
</path>
        <fillstroke/>
        <path>
<move x="53.33" y="20.31"/>
<line x="53.320004" y="20.34"/>
<line x="53.320004" y="20.35"/>
<curve x1="53.32" x2="53.33" x3="53.33" y1="20.34" y2="20.33" y3="20.31"/>
<close/>
</path>
        <fillstroke/>
        <fillcolor color="#E15343"/>
        <path>
<move x="40.66" y="6.63"/>
<line x="40.66" y="6.78"/>
<line x="12.66" y="6.78"/>
<line x="12.66" y="6.63"/>
<line x="12.18" y="6.63"/>
<line x="12.18" y="11.36"/>
<line x="41.14" y="11.36"/>
<line x="41.14" y="6.63"/>
<close/>
</path>
        <fillstroke/>
        <path>
<move x="37.66" y="0.0"/>
<line x="15.66" y="0.0"/>
<line x="12.66" y="3.0"/>
<line x="40.66" y="3.0"/>
<close/>
</path>
        <fillstroke/>
        <fillcolor color="#8C3323"/>
        <rect h="1.85" w="28.0" x="12.66" y="3.0"/>
        <fillstroke/>
        <rect h="4.76" w="0.69" x="40.45" y="6.63"/>
        <fillstroke/>
        <rect h="4.76" w="0.69" x="12.18" y="6.63"/>
        <fillstroke/>
        <path>
<move x="0.33" y="23.86"/>
<curve x1="0.22000001" x2="0.16000001" x3="0.16000001" y1="23.630001" y2="23.400002" y3="23.16"/>
<line x="0.33" y="23.86"/>
<close/>
</path>
        <fillstroke/>
        <path>
<move x="53.0" y="23.86"/>
<line x="53.16" y="23.16"/>
<curve x1="53.16" x2="53.11" x3="53.0" y1="23.4" y2="23.63" y3="23.86"/>
<close/>
</path>
        <fillstroke/>
        <path>
<move x="53.16" y="20.91"/>
<line x="53.16" y="23.16"/>
<line x="53.0" y="23.86"/>
<line x="53.0" y="21.6"/>
<close/>
</path>
        <fillstroke/>
        <path>
<move x="0.33" y="21.6"/>
<line x="0.33" y="23.86"/>
<line x="0.16" y="23.16"/>
<line x="0.16" y="20.91"/>
<close/>
</path>
        <fillstroke/>
        <restore/>
        <rect/>
        <stroke/>
        <fillcolor color="#8C3323"/>
        <path>
<move x="53.16" y="16.6"/>
<line x="53.16" y="18.86"/>
<curve x1="53.16" x2="41.3" x3="26.66" y1="22.310001" y2="25.09" y3="25.09"/>
<curve x1="12.0199995" x2="0.15999985" x3="0.15999985" y1="25.09" y2="22.31" y3="18.86"/>
<line x="0.15999985" y="16.6"/>
<curve x1="0.15999985" x2="12.0199995" x3="26.66" y1="20.050001" y2="22.83" y3="22.83"/>
<curve x1="41.3" x2="53.16" x3="53.16" y1="22.83" y2="20.06" y3="16.6"/>
<close/>
</path>
        <fillstroke/>
        <restore/>
        <rect/>
        <stroke/>
        <fillcolor color="#8C3323"/>
        <path>
<move x="53.16" y="16.61"/>
<line x="53.16" y="18.86"/>
<curve x1="53.16" x2="53.15" x3="53.14" y1="18.94" y2="19.02" y3="19.1"/>
<line x="53.14" y="16.85"/>
<curve x1="53.15" x2="53.16" x3="53.16" y1="16.77" y2="16.69" y3="16.61"/>
</path>
        <fillstroke/>
        <path>
<move x="53.14" y="16.85"/>
<line x="53.14" y="19.1"/>
<curve x1="53.13" x2="53.1" x3="53.07" y1="19.2" y2="19.29" y3="19.390001"/>
<line x="53.07" y="17.130001"/>
<curve x1="53.1" x2="53.13" x3="53.14" y1="17.04" y2="16.95" y3="16.85"/>
</path>
        <fillstroke/>
        <path>
<move x="53.07" y="17.13"/>
<line x="53.07" y="19.39"/>
<curve x1="53.02" x2="52.96" x3="52.88" y1="19.519999" y2="19.65" y3="19.779999"/>
<line x="52.88" y="17.519999"/>
<curve x1="52.96" x2="53.02" x3="53.07" y1="17.4" y2="17.27" y3="17.13"/>
</path>
        <fillstroke/>
        <path>
<move x="52.88" y="17.52"/>
<line x="52.88" y="19.78"/>
<curve x1="51.0" x2="39.980003" x3="26.660002" y1="22.79" y2="25.09" y3="25.09"/>
<curve x1="12.030002" x2="0.16000175" x3="0.16000175" y1="25.09" y2="22.31" y3="18.86"/>
<line x="0.16000175" y="16.61"/>
<curve x1="0.16000175" x2="12.030002" x3="26.660002" y1="20.060001" y2="22.83" y3="22.83"/>
<curve x1="39.98" x2="51.0" x3="52.88" y1="22.84" y2="20.54" y3="17.52"/>
</path>
        <fillstroke/>
        <fillcolor color="#E15343"/>
        <path>
<move x="26.66" y="10.38"/>
<curve x1="41.3" x2="53.16" x3="53.16" y1="10.38" y2="13.17" y3="16.61"/>
<curve x1="53.16" x2="41.3" x3="26.66" y1="20.060001" y2="22.84" y3="22.84"/>
<curve x1="12.03" x2="0.15999985" x3="0.15999985" y1="22.84" y2="20.06" y3="16.61"/>
<curve x1="0.16" x2="12.03" x3="26.66" y1="13.17" y2="10.38" y3="10.38"/>
<close/>
</path>
        <fillstroke/>
        <fillcolor color="#8C3323"/>
        <path>
<move x="53.0" y="21.6"/>
<line x="53.0" y="23.86"/>
<line x="44.33" y="60.85"/>
<line x="44.33" y="58.6"/>
<close/>
</path>
        <fillstroke/>
        <path>
<move x="9.0" y="58.6"/>
<line x="9.0" y="60.85"/>
<line x="0.33" y="23.86"/>
<line x="0.33" y="21.6"/>
<close/>
</path>
        <fillstroke/>
        <restore/>
        <rect/>
        <stroke/>
        <fillcolor color="#8C3323"/>
        <path>
<move x="44.33" y="58.6"/>
<line x="44.33" y="60.85"/>
<curve x1="44.33" x2="36.420002" x3="26.650002" y1="63.149998" y2="65.0" y3="65.0"/>
<curve x1="16.900002" x2="8.990002" x3="8.990002" y1="65.0" y2="63.15" y3="60.85"/>
<line x="8.990002" y="58.6"/>
<curve x1="8.990002" x2="16.900002" x3="26.650002" y1="60.899998" y2="62.75" y3="62.75"/>
<curve x1="36.42" x2="44.33" x3="44.33" y1="62.75" y2="60.9" y3="58.6"/>
<close/>
</path>
        <fillstroke/>
        <restore/>
        <rect/>
        <stroke/>
        <fillcolor color="#8C3323"/>
        <path>
<move x="44.33" y="58.6"/>
<line x="44.33" y="60.85"/>
<curve x1="44.33" x2="44.33" x3="44.320004" y1="60.91" y2="60.969997" y3="61.019997"/>
<line x="44.320004" y="58.76"/>
<curve x1="44.33" x2="44.33" x3="44.33" y1="58.71" y2="58.66" y3="58.6"/>
</path>
        <fillstroke/>
        <path>
<move x="44.32" y="58.76"/>
<line x="44.32" y="61.019997"/>
<curve x1="44.31" x2="44.29" x3="44.27" y1="61.079998" y2="61.149998" y3="61.209995"/>
<line x="44.27" y="58.959995"/>
<curve x1="44.29" x2="44.31" x3="44.32" y1="58.89" y2="58.83" y3="58.76"/>
</path>
        <fillstroke/>
        <path>
<move x="44.27" y="58.95"/>
<line x="44.27" y="61.21"/>
<curve x1="44.24" x2="44.19" x3="44.14" y1="61.29" y2="61.379997" y3="61.469997"/>
<line x="44.14" y="59.21"/>
<curve x1="44.19" x2="44.24" x3="44.27" y1="59.13" y2="59.04" y3="58.95"/>
</path>
        <fillstroke/>
        <path>
<move x="44.14" y="59.21"/>
<line x="44.14" y="61.469997"/>
<curve x1="42.89" x2="35.54" x3="26.66" y1="63.469997" y2="65.0" y3="65.0"/>
<curve x1="16.9" x2="9.0" x3="9.0" y1="65.0" y2="63.15" y3="60.85"/>
<line x="9.0" y="58.6"/>
<curve x1="9.0" x2="16.9" x3="26.66" y1="60.899998" y2="62.75" y3="62.75"/>
<curve x1="35.54" x2="42.89" x3="44.14" y1="62.75" y2="61.22" y3="59.21"/>
</path>
        <fillstroke/>
        <fillcolor color="#E15343"/>
        <path>
<move x="26.66" y="27.13"/>
<curve x1="40.3" x2="51.54" x3="53.0" y1="27.13" y2="24.72" y3="21.599998"/>
<line x="44.33" y="58.6"/>
<curve x1="44.33" x2="36.420002" x3="26.660002" y1="60.899998" y2="62.75" y3="62.75"/>
<curve x1="16.900002" x2="9.000002" x3="9.000002" y1="62.75" y2="60.9" y3="58.6"/>
<line x="0.33" y="21.6"/>
<curve x1="1.79" x2="13.02" x3="26.66" y1="24.72" y2="27.13" y3="27.13"/>
<close/>
</path>
        <fillstroke/>
    </foreground>
</shape>
<shape aspect="variable" h="66.0" name="EBS Volume" strokewidth="inherit" w="46.79">
<connections>
	<constraint x="0.5" y="0" perimeter="0" name="N"/>
	<constraint x="0.5" y="1" perimeter="0" name="S"/>
	<constraint x="0" y="0.5" perimeter="0" name="W"/>
	<constraint x="1" y="0.5" perimeter="0" name="E"/>
	<constraint x="0.16" y="0" perimeter="0" name="NW"/>
	<constraint x="0.84" y="0" perimeter="0" name="NE"/>
	<constraint x="0" y="1" perimeter="0" name="SW"/>
	<constraint x="1" y="1" perimeter="0" name="SE"/>
</connections>
    <foreground>
        <fillcolor color="#E15343"/>
        <rect h="51.37" w="46.79" x="0.0" y="12.14"/>
        <fillstroke/>
        <path>
<move x="39.36" y="0.0"/>
<line x="7.47" y="0.0"/>
<line x="0.61" y="6.42"/>
<line x="1.1" y="6.42"/>
<line x="45.72" y="6.42"/>
<close/>
</path>
        <fillstroke/>
        <fillcolor color="#8C3323"/>
        <rect h="2.49" w="46.79" x="0.0" y="63.51"/>
        <fillstroke/>
        <rect h="2.49" w="45.12" x="0.61" y="6.42"/>
        <fillstroke/>
    </foreground>
</shape>
<shape aspect="variable" h="71.9" name="Glacier" strokewidth="inherit" w="59.57">
<connections>
	<constraint x="0.5" y="0" perimeter="0" name="N"/>
	<constraint x="0.5" y="1" perimeter="0" name="S"/>
	<constraint x="0" y="0.5" perimeter="0" name="W"/>
	<constraint x="1" y="0.5" perimeter="0" name="E"/>
	<constraint x="0" y="0.21" perimeter="0" name="NW"/>
	<constraint x="1" y="0.21" perimeter="0" name="NE"/>
	<constraint x="0" y="0.79" perimeter="0" name="SW"/>
	<constraint x="1" y="0.79" perimeter="0" name="SE"/>
</connections>
    <foreground>
        <fillcolor color="#8C3123"/>
        <path>
<move x="29.79" y="53.35"/>
<line x="54.77" y="59.4"/>
<line x="54.77" y="12.49"/>
<line x="29.79" y="18.54"/>
<close/>
</path>
        <fillstroke/>
        <fillcolor color="#E05243"/>
        <path>
<move x="54.77" y="12.49"/>
<line x="59.57" y="14.89"/>
<line x="59.57" y="57.01"/>
<line x="54.77" y="59.41"/>
<close/>
</path>
        <fillstroke/>
        <path>
<move x="29.79" y="53.35"/>
<line x="4.8" y="59.4"/>
<line x="4.8" y="12.49"/>
<line x="29.79" y="18.54"/>
<close/>
</path>
        <fillstroke/>
        <fillcolor color="#8C3123"/>
        <path>
<move x="4.8" y="12.49"/>
<line x="0.0" y="14.89"/>
<line x="0.0" y="57.01"/>
<line x="4.8" y="59.41"/>
<close/>
</path>
        <fillstroke/>
        <fillcolor color="#E05243"/>
        <path>
<move x="29.79" y="71.9"/>
<line x="29.79" y="0.0"/>
<line x="40.68" y="5.45"/>
<line x="40.68" y="66.46"/>
<close/>
</path>
        <fillstroke/>
        <fillcolor color="#8C3123"/>
        <path>
<move x="29.79" y="71.9"/>
<line x="29.79" y="0.0"/>
<line x="18.89" y="5.45"/>
<line x="18.89" y="66.46"/>
<close/>
</path>
        <fillstroke/>
    </foreground>
</shape>
<shape aspect="variable" h="66.0" name="Glacier Archive" strokewidth="inherit" w="56.2">
<connections>
	<constraint x="0.5" y="0" perimeter="0" name="N"/>
	<constraint x="0.5" y="1" perimeter="0" name="S"/>
	<constraint x="0" y="0.5" perimeter="0" name="W"/>
	<constraint x="1" y="0.5" perimeter="0" name="E"/>
	<constraint x="0.015" y="0.095" perimeter="0" name="NW"/>
	<constraint x="0.985" y="0.095" perimeter="0" name="NE"/>
	<constraint x="0" y="1" perimeter="0" name="SW"/>
	<constraint x="1" y="1" perimeter="0" name="SE"/>
</connections>
    <foreground>
        <fillcolor color="#E15343"/>
        <rect h="51.37" w="26.45" x="0.0" y="12.14"/>
        <fillstroke/>
        <path>
<move x="26.45" y="0.0"/>
<line x="7.46" y="0.0"/>
<line x="0.6" y="6.42"/>
<line x="1.1" y="6.42"/>
<line x="26.45" y="6.42"/>
<close/>
</path>
        <fillstroke/>
        <fillcolor color="#8C3323"/>
        <rect h="2.49" w="26.45" x="0.0" y="63.51"/>
        <fillstroke/>
        <rect h="2.49" w="25.84" x="0.6" y="6.42"/>
        <fillstroke/>
        <fillcolor color="#E15343"/>
        <rect h="51.37" w="26.45" x="29.75" y="12.14"/>
        <fillstroke/>
        <path>
<move x="29.75" y="0.0"/>
<line x="48.73" y="0.0"/>
<line x="55.59" y="6.42"/>
<line x="55.1" y="6.42"/>
<line x="29.75" y="6.42"/>
<close/>
</path>
        <fillstroke/>
        <fillcolor color="#8C3323"/>
        <rect h="2.49" w="26.45" x="29.75" y="63.51"/>
        <fillstroke/>
        <rect h="2.49" w="25.84" x="29.75" y="6.42"/>
        <fillstroke/>
    </foreground>
</shape>
<shape aspect="variable" h="66.0" name="Glacier Vault" strokewidth="inherit" w="46.79">
<connections>
	<constraint x="0.5" y="0" perimeter="0" name="N"/>
	<constraint x="0.5" y="1" perimeter="0" name="S"/>
	<constraint x="0" y="0.5" perimeter="0" name="W"/>
	<constraint x="1" y="0.5" perimeter="0" name="E"/>
	<constraint x="0.015" y="0.095" perimeter="0" name="NW"/>
	<constraint x="0.975" y="0.095" perimeter="0" name="NE"/>
	<constraint x="0" y="1" perimeter="0" name="SW"/>
	<constraint x="1" y="1" perimeter="0" name="SE"/>
</connections>
    <foreground>
        <fillcolor color="#E15343"/>
        <rect h="51.37" w="46.79" x="0.0" y="12.14"/>
        <fillstroke/>
        <path>
<move x="39.35" y="0.0"/>
<line x="7.46" y="0.0"/>
<line x="0.61" y="6.42"/>
<line x="1.1" y="6.42"/>
<line x="45.72" y="6.42"/>
<close/>
</path>
        <fillstroke/>
        <fillcolor color="#8C3323"/>
        <rect h="2.49" w="46.79" x="0.0" y="63.51"/>
        <fillstroke/>
        <rect h="2.49" w="45.12" x="0.61" y="6.42"/>
        <fillstroke/>
        <path>
<move x="19.59" y="33.75"/>
<curve x1="20.69" x2="22.01" x3="23.39" y1="32.94" y2="32.49" y3="32.49"/>
<curve x1="25.16" x2="26.8" x3="28.0" y1="32.49" y2="33.2" y3="34.45"/>
<line x="31.53" y="32.760002"/>
<line x="31.53" y="30.760002"/>
<curve x1="31.53" x2="26.18" x3="23.39" y1="30.760002" y2="28.680002" y3="28.680002"/>
<curve x1="21.14" x2="16.41" x3="16.41" y1="28.680002" y2="29.460003" y3="29.460003"/>
<line x="16.41" y="31.460003"/>
<line x="19.59" y="33.75"/>
<close/>
</path>
        <fillstroke/>
        <path>
<move x="29.75" y="38.05"/>
<curve x1="29.79" x2="29.81" x3="29.81" y1="38.34" y2="38.63" y3="38.91"/>
<curve x1="29.81" x2="27.26" x3="24.279999" y1="42.02" y2="46.39" y3="46.97"/>
<line x="24.279999" y="48.97"/>
<curve x1="29.48" x2="33.76" x3="33.76" y1="48.52" y2="43.91" y3="38.600002"/>
<curve x1="33.76" x2="33.449997" x3="33.25" y1="37.74" y2="35.170002" y3="34.370003"/>
<line x="29.75" y="38.05"/>
<close/>
</path>
        <fillstroke/>
        <path>
<move x="20.64" y="44.71"/>
<line x="20.64" y="42.71"/>
<curve x1="20.64" x2="19.81" x3="19.32" y1="42.71" y2="43.0" y3="42.67"/>
<curve x1="18.23" x2="16.98" x3="16.98" y1="41.949997" y2="40.12" y3="38.91"/>
<curve x1="16.98" x2="17.08" x3="17.27" y1="38.26" y2="37.63" y3="37.01"/>
<line x="17.27" y="35.01"/>
<line x="14.1" y="32.73"/>
<curve x1="13.070001" x2="13.14" x3="13.14" y1="35.63" y2="37.15" y3="38.61"/>
<curve x1="13.14" x2="16.2" x3="20.3" y1="43.15" y2="47.22" y3="48.53"/>
<line x="20.64" y="44.71"/>
<close/>
</path>
        <fillstroke/>
        <fillcolor color="#FFFFFF"/>
        <path>
<move x="39.49" y="30.15"/>
<line x="38.63" y="28.35"/>
<line x="27.66" y="33.61"/>
<curve x1="26.67" x2="25.09" x3="23.31" y1="32.28" y2="31.42" y3="31.42"/>
<curve x1="21.849998" x2="20.529999" x3="19.55" y1="31.42" y2="32.0" y3="32.94"/>
<line x="10.179999" y="26.179998"/>
<line x="9.009999" y="27.809998"/>
<line x="18.4" y="34.57"/>
<curve x1="18.08" x2="17.9" x3="17.9" y1="35.26" y2="36.03" y3="36.84"/>
<curve x1="17.9" x2="19.46" x3="21.619999" y1="39.24" y2="41.27" y3="41.98"/>
<line x="20.619999" y="53.18"/>
<line x="22.619999" y="53.36"/>
<line x="23.609999" y="42.24"/>
<curve x1="26.46" x2="28.73" x3="28.73" y1="42.09" y2="39.730003" y3="36.84"/>
<curve x1="28.73" x2="28.66" x3="28.529999" y1="36.34" y2="35.87" y3="35.41"/>
<line x="39.49" y="30.15"/>
<close/>
</path>
        <fillstroke/>
        <path>
<move x="19.59" y="31.75"/>
<curve x1="20.69" x2="22.01" x3="23.39" y1="30.94" y2="30.49" y3="30.49"/>
<curve x1="25.16" x2="26.8" x3="28.0" y1="30.49" y2="31.199999" y3="32.45"/>
<line x="31.53" y="30.76"/>
<curve x1="29.67" x2="26.720001" x3="23.39" y1="28.29" y2="26.68" y3="26.68"/>
<curve x1="20.689999" x2="18.24" x3="16.41" y1="26.68" y2="27.74" y3="29.460001"/>
<line x="19.59" y="31.75"/>
<close/>
</path>
        <fillstroke/>
        <path>
<move x="29.75" y="36.05"/>
<curve x1="29.79" x2="29.81" x3="29.81" y1="36.34" y2="36.63" y3="36.91"/>
<curve x1="29.81" x2="27.59" x3="24.61" y1="40.02" y2="42.63" y3="43.21"/>
<line x="24.28" y="46.969997"/>
<curve x1="29.48" x2="33.56" x3="33.56" y1="46.519997" y2="42.159996" y3="36.839996"/>
<curve x1="33.56" x2="33.45" x3="33.25" y1="35.989998" y2="35.17" y3="34.369995"/>
<line x="29.75" y="36.05"/>
<close/>
</path>
        <fillstroke/>
        <path>
<move x="20.64" y="42.71"/>
<curve x1="18.42" x2="16.98" x3="16.98" y1="41.66" y2="39.42" y3="36.91"/>
<curve x1="16.98" x2="17.08" x3="17.27" y1="36.26" y2="35.63" y3="35.01"/>
<line x="14.1" y="32.73"/>
<curve x1="13.54" x2="13.2300005" x3="13.2300005" y1="33.989998" y2="35.38" y3="36.84"/>
<curve x1="13.2300005" x2="16.2" x3="20.300001" y1="41.38" y2="45.22" y3="46.53"/>
<line x="20.64" y="42.71"/>
<close/>
</path>
        <fillstroke/>
    </foreground>
</shape>
<shape aspect="variable" h="72.0" name="S3" strokewidth="inherit" w="59.57">
<connections>
	<constraint x="0.5" y="0" perimeter="0" name="N"/>
	<constraint x="0.5" y="1" perimeter="0" name="S"/>
	<constraint x="0" y="0.5" perimeter="0" name="W"/>
	<constraint x="1" y="0.5" perimeter="0" name="E"/>
	<constraint x="0" y="0.21" perimeter="0" name="NW"/>
	<constraint x="1" y="0.21" perimeter="0" name="NE"/>
	<constraint x="0" y="0.79" perimeter="0" name="SW"/>
	<constraint x="1" y="0.79" perimeter="0" name="SE"/>
</connections>
    <foreground>
        <fillcolor color="#8C3123"/>
        <path>
<move x="29.78" y="53.35"/>
<line x="54.77" y="59.4"/>
<line x="54.77" y="12.49"/>
<line x="29.78" y="18.54"/>
<close/>
</path>
        <fillstroke/>
        <fillcolor color="#E05243"/>
        <path>
<move x="54.77" y="12.49"/>
<line x="59.57" y="14.89"/>
<line x="59.57" y="57.01"/>
<line x="54.77" y="59.41"/>
<close/>
</path>
        <fillstroke/>
        <path>
<move x="40.68" y="20.86"/>
<line x="29.78" y="18.16"/>
<line x="29.78" y="0.0"/>
<line x="40.68" y="5.45"/>
<close/>
</path>
        <fillstroke/>
        <path>
<move x="29.78" y="72.0"/>
<line x="40.68" y="66.55"/>
<line x="40.68" y="51.15"/>
<line x="29.78" y="53.84"/>
<close/>
</path>
        <fillstroke/>
        <path>
<move x="40.68" y="43.71"/>
<line x="29.78" y="45.1"/>
<line x="29.78" y="26.94"/>
<line x="40.68" y="28.31"/>
<close/>
</path>
        <fillstroke/>
        <path>
<move x="29.78" y="53.35"/>
<line x="4.8" y="59.4"/>
<line x="4.8" y="12.49"/>
<line x="29.78" y="18.54"/>
<close/>
</path>
        <fillstroke/>
        <fillcolor color="#8C3123"/>
        <path>
<move x="4.8" y="12.49"/>
<line x="0.0" y="14.89"/>
<line x="0.0" y="57.01"/>
<line x="4.8" y="59.41"/>
<close/>
</path>
        <fillstroke/>
        <path>
<move x="18.89" y="20.86"/>
<line x="29.78" y="18.16"/>
<line x="29.78" y="0.0"/>
<line x="18.89" y="5.45"/>
<close/>
</path>
        <fillstroke/>
        <path>
<move x="29.78" y="72.0"/>
<line x="18.89" y="66.55"/>
<line x="18.89" y="51.15"/>
<line x="29.78" y="53.84"/>
<close/>
</path>
        <fillstroke/>
        <path>
<move x="18.89" y="43.71"/>
<line x="29.78" y="45.1"/>
<line x="29.78" y="26.94"/>
<line x="18.89" y="28.31"/>
<close/>
</path>
        <fillstroke/>
        <fillcolor color="#5E1F18"/>
        <path>
<move x="40.68" y="20.86"/>
<line x="29.78" y="22.84"/>
<line x="18.89" y="20.86"/>
<line x="29.78" y="18.16"/>
<close/>
</path>
        <fillstroke/>
        <fillcolor color="#F2B0A9"/>
        <path>
<move x="40.68" y="51.14"/>
<line x="29.78" y="49.15"/>
<line x="18.89" y="51.14"/>
<line x="29.78" y="53.86"/>
<close/>
</path>
        <fillstroke/>
    </foreground>
</shape>
<shape aspect="variable" h="56.39" name="S3 Bucket" strokewidth="inherit" w="54.81">
<connections>
	<constraint x="0.5" y="0" perimeter="0" name="N"/>
	<constraint x="0.5" y="1" perimeter="0" name="S"/>
	<constraint x="0.065" y="0.5" perimeter="0" name="W"/>
	<constraint x="0.935" y="0.5" perimeter="0" name="E"/>
	<constraint x="0" y="0.11" perimeter="0" name="NW"/>
	<constraint x="1" y="0.11" perimeter="0" name="NE"/>
	<constraint x="0.17" y="0.94" perimeter="0" name="SW"/>
	<constraint x="0.83" y="0.94" perimeter="0" name="SE"/>
</connections>
    <foreground>
        <save/>
        <save/>
        <save/>
        <save/>
        <fillcolor color="#8C3323"/>
        <path>
<move x="0.17" y="13.91"/>
<curve x1="0.060000002" x2="0.0" x3="0.0" y1="13.67" y2="13.43" y3="13.19"/>
<line x="0.17" y="13.91"/>
<close/>
</path>
        <fillstroke/>
        <path>
<move x="54.55" y="13.91"/>
<line x="54.719997" y="13.19"/>
<curve x1="54.72" x2="54.66" x3="54.55" y1="13.43" y2="13.67" y3="13.91"/>
<close/>
</path>
        <fillstroke/>
        <path>
<move x="54.72" y="10.87"/>
<line x="54.72" y="13.19"/>
<line x="54.55" y="13.91"/>
<line x="54.55" y="11.58"/>
<close/>
</path>
        <fillstroke/>
        <path>
<move x="0.17" y="11.58"/>
<line x="0.17" y="13.91"/>
<line x="0.0" y="13.19"/>
<line x="0.0" y="10.87"/>
<close/>
</path>
        <fillstroke/>
        <restore/>
        <rect/>
        <stroke/>
        <fillcolor color="#8C3323"/>
        <path>
<move x="54.72" y="6.42"/>
<line x="54.72" y="8.75"/>
<curve x1="54.72" x2="42.47" x3="27.36" y1="12.309999" y2="15.17" y3="15.17"/>
<curve x1="12.250001" x2="0.0" x3="0.0" y1="15.17" y2="12.31" y3="8.75"/>
<line x="0.0" y="6.42"/>
<curve x1="0.0" x2="12.25" x3="27.36" y1="9.98" y2="12.85" y3="12.85"/>
<curve x1="42.47" x2="54.72" x3="54.72" y1="12.85" y2="9.98" y3="6.42"/>
<close/>
</path>
        <fillstroke/>
        <restore/>
        <rect/>
        <stroke/>
        <fillcolor color="#8C3323"/>
        <path>
<move x="54.72" y="6.42"/>
<line x="54.72" y="8.75"/>
<curve x1="54.72" x2="54.710003" x3="54.690002" y1="8.83" y2="8.92" y3="9.0"/>
<line x="54.690002" y="6.6800003"/>
<curve x1="54.71" x2="54.72" x3="54.72" y1="6.59" y2="6.51" y3="6.42"/>
</path>
        <fillstroke/>
        <path>
<move x="54.69" y="6.68"/>
<line x="54.69" y="9.0"/>
<curve x1="54.68" x2="54.649998" x3="54.62" y1="9.1" y2="9.2" y3="9.3"/>
<line x="54.62" y="6.9700003"/>
<curve x1="54.65" x2="54.68" x3="54.69" y1="6.87" y2="6.78" y3="6.68"/>
</path>
        <fillstroke/>
        <path>
<move x="54.62" y="6.97"/>
<line x="54.62" y="9.299999"/>
<curve x1="54.57" x2="54.51" x3="54.42" y1="9.429999" y2="9.559999" y3="9.699999"/>
<line x="54.42" y="7.369999"/>
<curve x1="54.51" x2="54.57" x3="54.62" y1="7.24" y2="7.11" y3="6.97"/>
</path>
        <fillstroke/>
        <path>
<move x="54.42" y="7.37"/>
<line x="54.42" y="9.7"/>
<curve x1="52.48" x2="41.1" x3="27.349998" y1="12.809999" y2="15.18" y3="15.18"/>
<curve x1="12.249998" x2="-1.9073486E-6" x3="-1.9073486E-6" y1="15.18" y2="12.31" y3="8.75"/>
<line x="-1.9073486E-6" y="6.42"/>
<curve x1="-1.9073486E-6" x2="12.249998" x3="27.349998" y1="9.99" y2="12.85" y3="12.85"/>
<curve x1="41.1" x2="52.48" x3="54.42" y1="12.85" y2="10.48" y3="7.37"/>
</path>
        <fillstroke/>
        <fillcolor color="#E15343"/>
        <path>
<move x="27.35" y="0.0"/>
<curve x1="42.47" x2="54.72" x3="54.72" y1="0.0" y2="2.88" y3="6.42"/>
<curve x1="54.72" x2="42.47" x3="27.35" y1="9.99" y2="12.860001" y3="12.860001"/>
<curve x1="12.25" x2="0.0" x3="0.0" y1="12.860001" y2="9.990001" y3="6.4200006"/>
<curve x1="0.0" x2="12.25" x3="27.35" y1="2.88" y2="0.0" y3="0.0"/>
<close/>
</path>
        <fillstroke/>
        <fillcolor color="#8C3323"/>
        <path>
<move x="54.55" y="11.58"/>
<line x="54.55" y="13.91"/>
<line x="45.6" y="52.1"/>
<line x="45.6" y="49.78"/>
<close/>
</path>
        <fillstroke/>
        <path>
<move x="9.12" y="49.78"/>
<line x="9.12" y="52.1"/>
<line x="0.17" y="13.91"/>
<line x="0.17" y="11.58"/>
<close/>
</path>
        <fillstroke/>
        <restore/>
        <rect/>
        <stroke/>
        <fillcolor color="#8C3323"/>
        <path>
<move x="45.6" y="49.78"/>
<line x="45.6" y="52.1"/>
<curve x1="45.6" x2="37.44" x3="27.359999" y1="54.469997" y2="56.379997" y3="56.379997"/>
<curve x1="17.289999" x2="9.119999" x3="9.119999" y1="56.379997" y2="54.469997" y3="52.1"/>
<line x="9.119999" y="49.78"/>
<curve x1="9.119999" x2="17.289999" x3="27.359999" y1="52.149998" y2="54.059998" y3="54.059998"/>
<curve x1="37.44" x2="45.6" x3="45.6" y1="54.06" y2="52.15" y3="49.78"/>
<close/>
</path>
        <fillstroke/>
        <restore/>
        <rect/>
        <stroke/>
        <fillcolor color="#8C3323"/>
        <path>
<move x="45.6" y="49.78"/>
<line x="45.6" y="52.1"/>
<curve x1="45.6" x2="45.59" x3="45.579998" y1="52.16" y2="52.219997" y3="52.28"/>
<line x="45.579998" y="49.949997"/>
<curve x1="45.59" x2="45.6" x3="45.6" y1="49.89" y2="49.84" y3="49.78"/>
</path>
        <fillstroke/>
        <path>
<move x="45.58" y="49.95"/>
<line x="45.58" y="52.28"/>
<curve x1="45.58" x2="45.56" x3="45.54" y1="52.34" y2="52.399998" y3="52.469997"/>
<line x="45.54" y="50.14"/>
<curve x1="45.55" x2="45.58" x3="45.58" y1="50.08" y2="50.01" y3="49.95"/>
</path>
        <fillstroke/>
        <path>
<move x="45.54" y="50.14"/>
<line x="45.54" y="52.47"/>
<curve x1="45.5" x2="45.46" x3="45.4" y1="52.56" y2="52.65" y3="52.74"/>
<line x="45.4" y="50.410004"/>
<curve x1="45.46" x2="45.5" x3="45.54" y1="50.32" y2="50.23" y3="50.14"/>
</path>
        <fillstroke/>
        <path>
<move x="45.4" y="50.41"/>
<line x="45.4" y="52.739998"/>
<curve x1="44.11" x2="36.530003" x3="27.350002" y1="54.809998" y2="56.39" y3="56.39"/>
<curve x1="17.280003" x2="9.120003" x3="9.120003" y1="56.39" y2="54.48" y3="52.1"/>
<line x="9.120003" y="49.78"/>
<curve x1="9.120003" x2="17.280003" x3="27.350002" y1="52.149998" y2="54.059998" y3="54.059998"/>
<curve x1="36.53" x2="44.11" x3="45.4" y1="54.06" y2="52.48" y3="50.41"/>
</path>
        <fillstroke/>
        <fillcolor color="#E15343"/>
        <path>
<move x="27.35" y="17.29"/>
<curve x1="41.440002" x2="53.04" x3="54.550003" y1="17.29" y2="14.800001" y3="11.580001"/>
<line x="45.600002" y="49.780003"/>
<curve x1="45.600002" x2="37.43" x3="27.350002" y1="52.15" y2="54.06" y3="54.06"/>
<curve x1="17.280003" x2="9.120003" x3="9.120003" y1="54.06" y2="52.15" y3="49.780003"/>
<line x="0.17000294" y="11.580002"/>
<curve x1="1.68" x2="13.28" x3="27.35" y1="14.8" y2="17.29" y3="17.29"/>
<close/>
</path>
        <fillstroke/>
        <fillcolor color="#146EB4"/>
        <path>
<move x="54.78" y="10.86"/>
<curve x1="54.789997" x2="54.8" x3="54.809998" y1="10.9" y2="10.94" y3="10.969999"/>
<line x="54.8" y="10.909999"/>
<curve x1="54.79" x2="54.78" x3="54.78" y1="10.89" y2="10.88" y3="10.86"/>
<close/>
</path>
        <fillstroke/>
        <path>
<move x="54.75" y="10.77"/>
<curve x1="54.73" x2="54.71" x3="54.69" y1="10.71" y2="10.64" y3="10.570001"/>
<curve x1="54.7" x2="54.73" x3="54.75" y1="10.64" y2="10.71" y3="10.77"/>
<close/>
</path>
        <fillstroke/>
    </foreground>
</shape>
<shape aspect="variable" h="56.74" name="S3 Bucket with Objects" strokewidth="inherit" w="55.17">
<connections>
	<constraint x="0.5" y="0" perimeter="0" name="N"/>
	<constraint x="0.5" y="1" perimeter="0" name="S"/>
	<constraint x="0.065" y="0.5" perimeter="0" name="W"/>
	<constraint x="0.935" y="0.5" perimeter="0" name="E"/>
	<constraint x="0" y="0.11" perimeter="0" name="NW"/>
	<constraint x="1" y="0.11" perimeter="0" name="NE"/>
	<constraint x="0.17" y="0.94" perimeter="0" name="SW"/>
	<constraint x="0.83" y="0.94" perimeter="0" name="SE"/>
</connections>
    <foreground>
        <save/>
        <save/>
        <save/>
        <fillcolor color="#8C3323"/>
        <path>
<move x="55.18" y="6.43"/>
<line x="55.18" y="9.2"/>
<curve x1="55.18" x2="42.83" x3="27.6" y1="12.76" y2="15.639999" y3="15.639999"/>
<curve x1="12.35" x2="0.0" x3="0.0" y1="15.639999" y2="12.759999" y3="9.199999"/>
<line x="0.0" y="6.429999"/>
<curve x1="0.0" x2="12.35" x3="27.6" y1="9.989999" y2="12.859999" y3="12.859999"/>
<curve x1="42.83" x2="55.18" x3="55.18" y1="12.86" y2="9.99" y3="6.43"/>
<close/>
</path>
        <fillstroke/>
        <restore/>
        <rect/>
        <stroke/>
        <fillcolor color="#8C3323"/>
        <path>
<move x="55.17" y="6.43"/>
<line x="55.17" y="9.2"/>
<curve x1="55.17" x2="55.17" x3="55.149998" y1="9.29" y2="9.37" y3="9.45"/>
<line x="55.149998" y="6.68"/>
<curve x1="55.17" x2="55.17" x3="55.17" y1="6.6" y2="6.52" y3="6.43"/>
</path>
        <fillstroke/>
        <path>
<move x="55.15" y="6.68"/>
<line x="55.15" y="9.45"/>
<curve x1="55.13" x2="55.11" x3="55.08" y1="9.55" y2="9.65" y3="9.74"/>
<line x="55.08" y="6.97"/>
<curve x1="55.11" x2="55.14" x3="55.15" y1="6.87" y2="6.78" y3="6.68"/>
</path>
        <fillstroke/>
        <path>
<move x="55.08" y="6.97"/>
<line x="55.08" y="9.74"/>
<curve x1="55.030003" x2="54.97" x3="54.88" y1="9.88" y2="10.01" y3="10.139999"/>
<line x="54.88" y="7.3699994"/>
<curve x1="54.97" x2="55.03" x3="55.08" y1="7.24" y2="7.11" y3="6.97"/>
</path>
        <fillstroke/>
        <path>
<move x="54.88" y="7.37"/>
<line x="54.88" y="10.139999"/>
<curve x1="52.940002" x2="41.46" x3="27.59" y1="13.249999" y2="15.639999" y3="15.639999"/>
<curve x1="12.34" x2="0.0" x3="0.0" y1="15.639999" y2="12.759999" y3="9.199999"/>
<line x="0.0" y="6.429999"/>
<curve x1="0.0" x2="12.34" x3="27.59" y1="9.989999" y2="12.859999" y3="12.859999"/>
<curve x1="41.46" x2="52.94" x3="54.88" y1="12.86" y2="10.48" y3="7.37"/>
</path>
        <fillstroke/>
        <fillcolor color="#E15343"/>
        <path>
<move x="27.59" y="0.0"/>
<curve x1="42.83" x2="55.17" x3="55.17" y1="0.0" y2="2.87" y3="6.43"/>
<curve x1="55.17" x2="42.829998" x3="27.589998" y1="9.99" y2="12.86" y3="12.86"/>
<curve x1="12.339998" x2="-1.9073486E-6" x3="-1.9073486E-6" y1="12.86" y2="9.99" y3="6.43"/>
<curve x1="0.0" x2="12.34" x3="27.59" y1="2.87" y2="0.0" y3="0.0"/>
<close/>
</path>
        <fillstroke/>
        <fillcolor color="#8C3323"/>
        <path>
<move x="55.01" y="11.38"/>
<line x="55.01" y="14.15"/>
<line x="45.97" y="52.44"/>
<line x="45.26" y="50.63"/>
<close/>
</path>
        <fillstroke/>
        <path>
<move x="9.2" y="49.67"/>
<line x="9.2" y="52.44"/>
<line x="0.16" y="14.15"/>
<line x="0.16" y="11.38"/>
<close/>
</path>
        <fillstroke/>
        <restore/>
        <rect/>
        <stroke/>
        <fillcolor color="#8C3323"/>
        <path>
<move x="45.98" y="49.67"/>
<line x="45.98" y="52.44"/>
<curve x1="45.98" x2="37.76" x3="27.6" y1="54.829998" y2="56.739998" y3="56.739998"/>
<curve x1="17.440002" x2="9.200001" x3="9.200001" y1="56.739998" y2="54.829998" y3="52.44"/>
<line x="9.200001" y="49.67"/>
<curve x1="9.200001" x2="17.43" x3="27.6" y1="52.059998" y2="53.969997" y3="53.969997"/>
<curve x1="37.77" x2="45.98" x3="45.98" y1="53.969997" y2="52.05" y3="49.67"/>
<close/>
</path>
        <fillstroke/>
        <restore/>
        <rect/>
        <stroke/>
        <fillcolor color="#8C3323"/>
        <path>
<move x="45.97" y="49.67"/>
<line x="45.97" y="52.44"/>
<curve x1="45.97" x2="45.97" x3="45.960003" y1="52.5" y2="52.55" y3="52.609997"/>
<line x="45.960003" y="49.839996"/>
<curve x1="45.97" x2="45.97" x3="45.97" y1="49.78" y2="49.72" y3="49.67"/>
</path>
        <fillstroke/>
        <path>
<move x="45.96" y="49.84"/>
<line x="45.96" y="52.61"/>
<curve x1="45.95" x2="45.93" x3="45.91" y1="52.670002" y2="52.74" y3="52.8"/>
<line x="45.91" y="50.03"/>
<curve x1="45.93" x2="45.95" x3="45.96" y1="49.97" y2="49.9" y3="49.84"/>
</path>
        <fillstroke/>
        <path>
<move x="45.91" y="50.03"/>
<line x="45.91" y="52.8"/>
<curve x1="45.88" x2="45.829998" x3="45.78" y1="52.899998" y2="52.98" y3="53.07"/>
<line x="45.78" y="50.3"/>
<curve x1="45.83" x2="45.88" x3="45.91" y1="50.21" y2="50.12" y3="50.03"/>
</path>
        <fillstroke/>
        <path>
<move x="46.26" y="49.38"/>
<line x="45.78" y="53.07"/>
<curve x1="44.48" x2="36.84" x3="27.589998" y1="55.16" y2="56.739998" y3="56.739998"/>
<curve x1="17.429998" x2="9.199999" x3="9.199999" y1="56.739998" y2="54.829998" y3="52.44"/>
<line x="9.199999" y="49.67"/>
<curve x1="9.199999" x2="17.429998" x3="27.589998" y1="52.059998" y2="53.969997" y3="53.969997"/>
<curve x1="36.839996" x2="44.479996" x3="45.78" y1="53.969997" y2="52.389996" y3="50.299995"/>
</path>
        <fillstroke/>
        <fillcolor color="#E15343"/>
        <path>
<move x="27.59" y="17.12"/>
<curve x1="41.83" x2="53.55" x3="55.010002" y1="17.12" y2="14.610001" y3="11.380001"/>
<line x="45.97" y="49.670002"/>
<curve x1="45.97" x2="37.760002" x3="27.590002" y1="52.06" y2="53.97" y3="53.97"/>
<curve x1="17.420002" x2="9.200003" x3="9.200003" y1="53.97" y2="52.06" y3="49.670002"/>
<line x="0.16000271" y="11.380001"/>
<curve x1="1.63" x2="13.36" x3="27.59" y1="14.61" y2="17.12" y3="17.12"/>
<close/>
</path>
        <fillstroke/>
        <fillcolor color="#FFFFFF"/>
        <rect h="11.4" w="11.48" x="21.35" y="21.23"/>
        <fillstroke/>
        <ellipse h="11.24" w="11.32" x="12.22" y="36.65"/>
        <fillstroke/>
        <path>
<move x="41.68" y="47.63"/>
<line x="30.33" y="47.63"/>
<line x="36.01" y="37.16"/>
<close/>
</path>
        <fillstroke/>
    </foreground>
</shape>
<shape aspect="variable" h="40.77" name="S3 Objects" strokewidth="inherit" w="37.53">
<connections>
	<constraint x="0.5" y="0" perimeter="0" name="N"/>
	<constraint x="0.5" y="1" perimeter="0" name="S"/>
	<constraint x="0" y="0.5" perimeter="0" name="W"/>
	<constraint x="1" y="0.5" perimeter="0" name="E"/>
	<constraint x="0.14" y="0.14" perimeter="0" name="NW"/>
	<constraint x="0.86" y="0.14" perimeter="0" name="NE"/>
	<constraint x="0.14" y="0.86" perimeter="0" name="SW"/>
	<constraint x="0.86" y="0.86" perimeter="0" name="SE"/>
</connections>
    <foreground>
        <save/>
        <save/>
        <fillcolor color="#E15343"/>
        <path>
<move x="18.77" y="0.0"/>
<curve x1="29.14" x2="37.53" x3="37.53" y1="0.0" y2="8.33" y3="18.62"/>
<curve x1="37.53" x2="29.14" x3="18.769999" y1="28.910002" y2="37.25" y3="37.25"/>
<curve x1="8.399998" x2="0.0" x3="0.0" y1="37.25" y2="28.91" y3="18.62"/>
<curve x1="0.0" x2="8.41" x3="18.77" y1="8.330002" y2="0.0" y3="0.0"/>
<close/>
</path>
        <fillstroke/>
        <restore/>
        <rect/>
        <stroke/>
        <fillcolor color="#8C3323"/>
        <path>
<move x="37.52" y="18.62"/>
<line x="37.52" y="22.140001"/>
<curve x1="37.52" x2="29.130001" x3="18.77" y1="32.43" y2="40.78" y3="40.78"/>
<curve x1="8.41" x2="0.0" x3="0.0" y1="40.78" y2="32.43" y3="22.14"/>
<line x="0.0" y="18.619999"/>
<curve x1="0.0" x2="8.4" x3="18.77" y1="28.91" y2="37.26" y3="37.26"/>
<curve x1="29.140001" x2="37.52" x3="37.52" y1="37.26" y2="28.91" y3="18.62"/>
<close/>
</path>
        <fillstroke/>
        <restore/>
        <rect/>
        <stroke/>
        <fillcolor color="#8C3323"/>
        <path>
<move x="37.53" y="18.62"/>
<line x="37.53" y="22.140001"/>
<curve x1="37.53" x2="37.469997" x3="37.34" y1="23.04" y2="23.93" y3="24.800001"/>
<line x="37.34" y="21.28"/>
<curve x1="37.46" x2="37.53" x3="37.53" y1="20.41" y2="19.52" y3="18.62"/>
</path>
        <fillstroke/>
        <path>
<move x="37.34" y="21.28"/>
<line x="37.34" y="24.800001"/>
<curve x1="37.19" x2="36.96" x3="36.64" y1="25.830002" y2="26.84" y3="27.810001"/>
<line x="36.64" y="24.29"/>
<curve x1="36.96" x2="37.19" x3="37.34" y1="23.32" y2="22.32" y3="21.28"/>
</path>
        <fillstroke/>
        <path>
<move x="36.64" y="24.29"/>
<line x="36.64" y="27.810001"/>
<curve x1="36.28" x2="35.8" x3="35.23" y1="28.95" y2="30.050001" y3="31.090002"/>
<line x="35.23" y="27.57"/>
<curve x1="35.8" x2="36.28" x3="36.64" y1="26.53" y2="25.43" y3="24.29"/>
</path>
        <fillstroke/>
        <path>
<move x="35.23" y="27.57"/>
<line x="35.23" y="31.09"/>
<curve x1="32.04" x2="25.869999" x3="18.77" y1="36.86" y2="40.77" y3="40.77"/>
<curve x1="8.410001" x2="0.0" x3="0.0" y1="40.77" y2="32.42" y3="22.140001"/>
<line x="0.0" y="18.62"/>
<curve x1="0.0" x2="8.41" x3="18.77" y1="28.900002" y2="37.25" y3="37.25"/>
<curve x1="25.87" x2="32.04" x3="35.23" y1="37.25" y2="33.34" y3="27.57"/>
</path>
        <fillstroke/>
    </foreground>
</shape>
</shapes>